LICENSE
README.md
setup.py
./__init__.py
./data.py
./functions.py
./playground.py
./setup.py
./experiments/__init__.py
./experiments/_alpha.py
./experiments/_drum.py
./experiments/_nasty_drum.py
./experiments/dummy_drum.py
./instruments/__init__.py
./instruments/_adalm2000.py
./instruments/_auber_syl53x2p.py
./instruments/_gui_tools.py
./instruments/_keithley_dmm.py
./instruments/_serial_tools.py
./instruments/_sillyscope.py
./instruments/_soundcard.py
./instruments/_test_adalm2000.py
./instruments/_visa_tools.py
./plot_scripts/ADALM2000/li_sweep_magphase.py
./plot_scripts/ADALM2000/li_sweep_magphase_log.py
./plot_scripts/quadratures/mag_phase_linear.py
./plot_scripts/quadratures/mag_phase_log.py
./tests/mcphysics_tests.py
./tests/data/background.Chn
./tests/data/image.jpg
./tests/data/signal.Chn
McPhysics.egg-info/PKG-INFO
McPhysics.egg-info/SOURCES.txt
McPhysics.egg-info/dependency_links.txt
McPhysics.egg-info/top_level.txt