Metadata-Version: 2.1
Name: McPhysics
Version: 1.5.14
Summary: Useful tools for the McGill Undergraduate Physics Labs
Home-page: https://github.com/sankeylab/mcphysics
Author: Jack Sankey
Author-email: jack.sankey@gmail.com
License-File: LICENSE
